CHANGELOG.md
README.md
acme.ini.default
acme.py
setup.py
ACME_oneM2M_CSE.egg-info/PKG-INFO
ACME_oneM2M_CSE.egg-info/SOURCES.txt
ACME_oneM2M_CSE.egg-info/dependency_links.txt
ACME_oneM2M_CSE.egg-info/requires.txt
ACME_oneM2M_CSE.egg-info/top_level.txt
acme/AnnouncementManager.py
acme/CSE.py
acme/Configuration.py
acme/Constants.py
acme/Dispatcher.py
acme/EventManager.py
acme/GroupManager.py
acme/HttpServer.py
acme/Importer.py
acme/Logging.py
acme/NotificationManager.py
acme/RegistrationManager.py
acme/RemoteCSEManager.py
acme/SecurityManager.py
acme/Statistics.py
acme/Storage.py
acme/Utils.py
acme/__init__.py
acme/__pycache__/AnnouncementManager.cpython-38.pyc
acme/__pycache__/CSE.cpython-38.pyc
acme/__pycache__/Configuration.cpython-38.pyc
acme/__pycache__/Constants.cpython-38.pyc
acme/__pycache__/Dispatcher.cpython-38.pyc
acme/__pycache__/EventManager.cpython-38.pyc
acme/__pycache__/GroupManager.cpython-38.pyc
acme/__pycache__/HttpServer.cpython-38.pyc
acme/__pycache__/Importer.cpython-38.pyc
acme/__pycache__/Logging.cpython-38.pyc
acme/__pycache__/NotificationManager.cpython-38.pyc
acme/__pycache__/RegistrationManager.cpython-38.pyc
acme/__pycache__/RemoteCSEManager.cpython-38.pyc
acme/__pycache__/SecurityManager.cpython-38.pyc
acme/__pycache__/Statistics.cpython-38.pyc
acme/__pycache__/Storage.cpython-38.pyc
acme/__pycache__/Utils.cpython-38.pyc
acme/helpers/BackgroundWorker.py
acme/helpers/__init__.py
acme/helpers/__pycache__/BackgroundWorker.cpython-38.pyc
acme/helpers/__pycache__/__init__.cpython-38.pyc
acme/resources/ACP.py
acme/resources/AE.py
acme/resources/ANDI.py
acme/resources/ANI.py
acme/resources/BAT.py
acme/resources/CIN.py
acme/resources/CNT.py
acme/resources/CNT_LA.py
acme/resources/CNT_OL.py
acme/resources/CSEBase.py
acme/resources/CSR.py
acme/resources/DVC.py
acme/resources/DVI.py
acme/resources/EVL.py
acme/resources/FCI.py
acme/resources/FCNT.py
acme/resources/FCNT_LA.py
acme/resources/FCNT_OL.py
acme/resources/FWR.py
acme/resources/GRP.py
acme/resources/GRP_FOPT.py
acme/resources/MEM.py
acme/resources/MgmtObj.py
acme/resources/NOD.py
acme/resources/RBO.py
acme/resources/Resource.py
acme/resources/SUB.py
acme/resources/SWR.py
