Metadata-Version: 2.1
Name: ACME-oneM2M-CSE
Version: 0.3.0
Summary: An open source CSE Middleware for Education.
Home-page: https://github.com/ankraft/ACME-oneM2M-CSE
Author: Andreas Kraft
Author-email: onem2m@mheg.org
License: BSD 3-Clause
Keywords: onem2m cse framework
Platform: UNKNOWN
Classifier: Programming Language :: Python :: 3
Classifier: License :: OSI Approved :: BSD License
Classifier: Operating System :: OS Independent
Requires-Python: >=3.8
